cloudconvert/__init__.py
cloudconvert/cloudconvertrestclient.py
cloudconvert/config.py
cloudconvert/environment_vars.py
cloudconvert/job.py
cloudconvert/resource.py
cloudconvert/task.py
cloudconvert/utils.py
cloudconvert/webhook.py
cloudconvert/exceptions/__init__.py
cloudconvert/exceptions/exceptions.py
tests/__init__.py
tests/integration/__init__.py
tests/integration/testJobs.py
tests/integration/testTasks.py
tests/unit/__init__.py
tests/unit/testJob.py
tests/unit/testTask.py
tests/unit/testWebhookSignature.py
cloudconvert-2.0.0.dist-info/LICENCE
cloudconvert-2.0.0.dist-info/METADATA
cloudconvert-2.0.0.dist-info/WHEEL
cloudconvert-2.0.0.dist-info/top_level.txt
cloudconvert-2.0.0.dist-info/RECORD
