Metadata-Version: 2.1
Name: cloudconvert
Version: 2.0.0
Summary: Python REST API wrapper for cloud convert
Home-page: https://github.com/cloudconvert/cloudconvert-python
Author: Josias Montag
Author-email: josias@montag.info
License: UNKNOWN
Platform: UNKNOWN
Classifier: Programming Language :: Python :: 3
Classifier: License :: OSI Approved :: MIT License
Classifier: Operating System :: OS Independent
Requires-Dist: requests
Requires-Dist: urllib3
